calendar_hj3415/__init__.py
calendar_hj3415/admin.py
calendar_hj3415/apps.py
calendar_hj3415/models.py
calendar_hj3415/urls.py
calendar_hj3415/utils.py
calendar_hj3415/views.py
calendar_hj3415/migrations/__init__.py
calendar_hj3415/static/calendar_hj3415/calendar.css
calendar_hj3415/static/calendar_hj3415/calendar.js
calendar_hj3415/templates/calendar_hj3415/_month.html
calendar_hj3415/templates/calendar_hj3415/modal.html
calendar_hj3415/templatetags/__init__.py
calendar_hj3415/templatetags/calendar_tags.py
calendar_hj3415-0.0.5.dist-info/WHEEL
calendar_hj3415-0.0.5.dist-info/METADATA
calendar_hj3415-0.0.5.dist-info/RECORD
