Metadata-Version: 2.4
Name: calendar-hj3415
Version: 0.0.5
Summary: calendar-hj3415 is the program for opening the modal calendar window
Author-email: Hyungjin Kim <hj3415@gmail.com>
Classifier: License :: OSI Approved :: MIT License
Requires-Dist: django
Project-URL: Home, https://www.hyungjin.kr
